odoo9_addon_web_widget_timepicker-9.0.1.0.0.99.dev5-nspkg.pth
odoo_addons/web_widget_timepicker/README.rst
odoo_addons/web_widget_timepicker/__init__.py
odoo_addons/web_widget_timepicker/__openerp__.py
odoo_addons/web_widget_timepicker/images/form_view.png
odoo_addons/web_widget_timepicker/images/picker.png
odoo_addons/web_widget_timepicker/static/description/icon.png
odoo_addons/web_widget_timepicker/static/src/css/web_widget_timepicker.css
odoo_addons/web_widget_timepicker/static/src/js/web_widget_timepicker.js
odoo_addons/web_widget_timepicker/static/src/lib/jquery.timepicker/jquery.timepicker.css
odoo_addons/web_widget_timepicker/static/src/lib/jquery.timepicker/jquery.timepicker.js
odoo_addons/web_widget_timepicker/static/src/xml/web_widget_timepicker.xml
odoo_addons/web_widget_timepicker/views/web_widget_timepicker_assets.xml
odoo9_addon_web_widget_timepicker-9.0.1.0.0.99.dev5.dist-info/METADATA
odoo9_addon_web_widget_timepicker-9.0.1.0.0.99.dev5.dist-info/WHEEL
odoo9_addon_web_widget_timepicker-9.0.1.0.0.99.dev5.dist-info/namespace_packages.txt
odoo9_addon_web_widget_timepicker-9.0.1.0.0.99.dev5.dist-info/top_level.txt
odoo9_addon_web_widget_timepicker-9.0.1.0.0.99.dev5.dist-info/RECORD
